pype/__init__.py
pype/__main__.py
pype/_version.py
pype/app.py
thru-0.0.27.dist-info/METADATA
thru-0.0.27.dist-info/RECORD
thru-0.0.27.dist-info/WHEEL
thru-0.0.27.dist-info/entry_points.txt
thru-0.0.27.dist-info/top_level.txt
