Metadata-Version: 2.1
Name: thru
Version: 0.0.27
Summary: Command line pipes for python.
Home-page: https://github.com/me/myproject
Author: Me
Author-email: me@example.com
License: Apache License 2.0
Platform: UNKNOWN
Classifier: License :: OSI Approved :: Apache Software License
Classifier: Programming Language :: Python
Classifier: Programming Language :: Python :: 3
Classifier: Programming Language :: Python :: 3.6
Classifier: Programming Language :: Python :: Implementation :: CPython
Classifier: Programming Language :: Python :: Implementation :: PyPy
Requires-Python: >=3.6.0
Requires-Dist: attrs
Requires-Dist: click
Requires-Dist: click-default-group
Requires-Dist: toolz
Requires-Dist: twisted
